{
  "info": {
    "url_png_icon_64x64": "https://www.adasrn.com/ADASRN_64x64.png",
    "url_png_logo": "https://www.adasrn.com/ADASRN_1024x1024.png",
    "location": "Malaysia, Asia",
    "social": {
      "twitter_handle": "ADASRN1",
      "telegram_handle": "Sayshar",
      "facebook_handle": "ADASRN1",
      "youtube_handle": "",
      "twitch_handle": "",
      "discord_handle": "Sayshar#0645",
      "github_handle": "sayshar"
    },
    "company": {
      "name": "",
      "addr": "",
      "city": "",
      "country": "",
      "company_id": "",
      "vat_id": ""
    },
    "about": {
      "me": "We are Malaysians who want to participate in the Cardano network as we believe DeFi is the future. We are donating some of our proceedings to charity once we are profitable. Follow our Twitter page to keep up with us.",
      "server": "We have 3 separate bare metal nodes which comprise of 2 Relay nodes and 1 Block producing node. All three nodes run on Ubuntu 20.04 LTS server edition for maximum reliability. We are excited to let you know that two of our nodes are run from Raspberry Pi 4B 8GB with binaries compiled from source for the aarch64 architecture. We also have an additional x86-64 linux-PC to act as a backup relay/block node if needed.",
      "company": ""
    },
    "rss": "http(s) url to valid RSS feed"
  },
  "telegram-admin-handle": [
    ""
  ],
  "my-pool-ids": [
    "cc1b1c03798884c636703443a23b8d9e827d6c0417921600394198a0"
  ],
  "when-satured-then-recommend": [
    "cc1b1c03798884c636703443a23b8d9e827d6c0417921600394198a0"
  ]
}
